encryption_package/__init__.py
encryption_package/encryption.py
nitrogen_package/Nitrogen_Estimation_Methods.py
nitrogen_package/__init__.py
sorting_package/__init__.py
sorting_package/sorting.py
PHDCSF21M501_PythonLib-3.0.0.dist-info/LICENSE.txt
PHDCSF21M501_PythonLib-3.0.0.dist-info/METADATA
PHDCSF21M501_PythonLib-3.0.0.dist-info/WHEEL
PHDCSF21M501_PythonLib-3.0.0.dist-info/top_level.txt
PHDCSF21M501_PythonLib-3.0.0.dist-info/RECORD
