Metadata-Version: 2.1
Name: PHDCSF21M501-PythonLib
Version: 3.0.0
Summary: A simple Python library
Home-page: https://github.com/Amjad-Afzaal/PHDCSF21M501_TTDS/tree/master/Assignments/Asg1/PHDCSF21M501_PythonLib
Author: Amjad Afzaal
Author-email: PHDCSF21M501@pucit.edu.pk
Project-URL: Bug Tracker, https://github.com/Amjad-Afzaal/PHDCSF21M501_TTDS/issues
Project-URL: repository, https://github.com/Amjad-Afzaal/PHDCSF21M501_TTDS
Classifier: Programming Language :: Python :: 3
Classifier: License :: OSI Approved :: GNU General Public License v3 (GPLv3)
Classifier: Operating System :: OS Independent
Requires-Python: >=3.6
License-File: LICENSE.txt
